Metadata-Version: 1.1
Name: classbasedmodule
Version: 0.1.1
Summary: Decorator overwriting sys.modules with a class instance as the module.
Home-page: https://github.com/sjoerdjob/python-classbasedmodule
Author: Sjoerd Job Postmus
Author-email: sjoerdjob@sjec.nl
License: MIT license
Keywords: classbasedmodule
Platform: UNKNOWN
Classifier: Development Status :: 2 - Pre-Alpha
Classifier: Intended Audience :: Developers
Classifier: License :: OSI Approved :: MIT License
Classifier: Natural Language :: English
Classifier: Programming Language :: Python :: 2
Classifier: Programming Language :: Python :: 2.6
Classifier: Programming Language :: Python :: 2.7
Classifier: Programming Language :: Python :: 3
Classifier: Programming Language :: Python :: 3.3
Classifier: Programming Language :: Python :: 3.4
Classifier: Programming Language :: Python :: 3.5
